LICENSE
README.md
setup.py
NeuralNetworkTools/__init__.py
NeuralNetworkTools/activations.py
NeuralNetworkTools/loss.py
NeuralNetworkTools/metrics.py
NeuralNetworkTools/utils.py
NeuralNetworkTools.egg-info/PKG-INFO
NeuralNetworkTools.egg-info/SOURCES.txt
NeuralNetworkTools.egg-info/dependency_links.txt
NeuralNetworkTools.egg-info/top_level.txt